molywood/__init__.py
molywood/graphics_actions.py
molywood/moly.py
molywood/tcl_actions.py
molywood-0.247.dist-info/LICENSE
molywood-0.247.dist-info/METADATA
molywood-0.247.dist-info/WHEEL
molywood-0.247.dist-info/entry_points.txt
molywood-0.247.dist-info/top_level.txt
molywood-0.247.dist-info/RECORD
