Metadata-Version: 2.1
Name: molywood
Version: 0.247
Summary: A script to automate the production of molecular movies in VMD
Home-page: https://gitlab.com/KomBioMol/molywood
Author: Milosz Wieczor
Author-email: milafternoon@gmail.com
License: GNU GPLv3
Requires-Python: >=3.4
License-File: LICENSE
Requires-Dist: setuptools>=24.2.0
Requires-Dist: pip>=9.0.0
